pandasrw.py
pandasrw-0.0.7.dist-info/METADATA
pandasrw-0.0.7.dist-info/WHEEL
pandasrw-0.0.7.dist-info/top_level.txt
pandasrw-0.0.7.dist-info/RECORD
