Metadata-Version: 2.1
Name: pandasrw
Version: 0.0.7
Summary: A pandas IO library for efficiently reading and writing excel, csv, and xlsx files
Home-page: https://github.com/stormtozero/pandasrw
Author: storm
Author-email: pandasrw Author <41915460@163.com>
License: MIT
Project-URL: Homepage, https://github.com/stormtozero/pandasrw
Classifier: Programming Language :: Python :: 3
Classifier: License :: OSI Approved :: MIT License
Classifier: Operating System :: OS Independent
Requires-Python: >=3.8
Requires-Dist: polars
Requires-Dist: xlwings
Requires-Dist: datetime
Requires-Dist: chardet
Requires-Dist: xlsx2csv
Requires-Dist: pandas >=2.2.0
Requires-Dist: xlsxwriter
Requires-Dist: python-calamine
